taskbench/__init__.py
taskbench/__main__.py
taskbench-1.2.1.dist-info/METADATA
taskbench-1.2.1.dist-info/WHEEL
taskbench-1.2.1.dist-info/entry_points.txt
taskbench-1.2.1.dist-info/top_level.txt
taskbench-1.2.1.dist-info/RECORD
